README.md
license.txt
setup.py
Perfole/Perfole.py
Perfole/__init__.py
Perfole.egg-info/PKG-INFO
Perfole.egg-info/SOURCES.txt
Perfole.egg-info/dependency_links.txt
Perfole.egg-info/requires.txt
Perfole.egg-info/top_level.txt