Metadata-Version: 2.1
Name: Perfole
Version: 0.0.6
Summary: Measure performance
Author: breeze-testing
License: license.txt
License-File: license.txt
